pretty_html_table/__init__.py
pretty_html_table/pretty_html_table.py
pretty_html_table-0.9.15.dist-info/LICENSE.txt
pretty_html_table-0.9.15.dist-info/METADATA
pretty_html_table-0.9.15.dist-info/WHEEL
pretty_html_table-0.9.15.dist-info/top_level.txt
pretty_html_table-0.9.15.dist-info/RECORD
