Metadata-Version: 2.1
Name: pretty_html_table
Version: 0.9.15
Summary: Make pandas dataframe looking pretty again
Home-page: https://github.com/sbi-rviot/ph_table
Author: Renaud Viot
Author-email: renaud.viot@simply-bi.com
License: UNKNOWN
Platform: UNKNOWN
Classifier: Programming Language :: Python :: 3
Classifier: License :: OSI Approved :: MIT License
Classifier: Operating System :: OS Independent
